mymathpack/__init__.py
mymathpack/math_operations.py
mymathpack-0.1.dist-info/METADATA
mymathpack-0.1.dist-info/WHEEL
mymathpack-0.1.dist-info/top_level.txt
mymathpack-0.1.dist-info/RECORD
